nessiev2_unofficial/__init__.py
nessiev2_unofficial/catalog.py
nessiev2_unofficial/client.py
nessiev2_unofficial/test_client.py
nessiev2_unofficial/test_objects.py
nessiev2_unofficial/generators/__init__.py
nessiev2_unofficial/utils/__init__.py
nessiev2_unofficial-0.0.18.dist-info/LICENSE
nessiev2_unofficial-0.0.18.dist-info/METADATA
nessiev2_unofficial-0.0.18.dist-info/WHEEL
nessiev2_unofficial-0.0.18.dist-info/top_level.txt
nessiev2_unofficial-0.0.18.dist-info/RECORD
