Metadata-Version: 2.1
Name: nessiev2-unofficial
Version: 0.0.18
Summary: An unofficial example of a Nessie V2 Client
Author-email: Alex Merced <alex.merced@dremio.com>
Project-URL: Homepage, https://github.com/AlexMercedCoder/UnofficialNessieV2ClientPython
Project-URL: Bug Tracker, https://github.com/AlexMercedCoder/UnofficialNessieV2ClientPython
Classifier: Programming Language :: Python :: 3
Classifier: License :: OSI Approved :: MIT License
Classifier: Operating System :: OS Independent
Requires-Python: >=3.7
License-File: LICENSE
Requires-Dist: requests (~=2.28.2)
Requires-Dist: requests-aws4auth (~=1.2.3)
Requires-Dist: botocore (~=1.29.159)
